werkflow_appito/__init__.py
werkflow_appito/appito.py
werkflow_appito/models/__init__.py
werkflow_appito/models/api/__init__.py
werkflow_appito/models/api/appito_get_environment_request.py
werkflow_appito/models/api/appito_get_environment_response.py
werkflow_appito/models/api/appito_upload_table_request.py
werkflow_appito/models/environment/__init__.py
werkflow_appito/models/environment/appito_environment.py
werkflow_appito/models/shared/__init__.py
werkflow_appito/models/shared/appito_credentials.py
werkflow_appito/models/shared/appito_region.py
werkflow_appito/models/shared/appito_region_url_map.py
werkflow_appito-0.1.0.dist-info/licenses/LICENSE
werkflow_appito-0.1.0.dist-info/METADATA
werkflow_appito-0.1.0.dist-info/WHEEL
werkflow_appito-0.1.0.dist-info/top_level.txt
werkflow_appito-0.1.0.dist-info/RECORD
