Metadata-Version: 2.4
Name: werkflow-appito
Version: 0.1.0
Summary: An IBM Appito module for Werkflow.
Author-email: Ada Lundhe <adalundhe@lundhe.audio>
Keywords: pypi,cicd,python,werkflow,workflow,werkflow-core,appito,boto3,ibm
Classifier: Programming Language :: Python :: 3.11
Classifier: Programming Language :: Python :: 3.12
Classifier: Programming Language :: Python :: 3.13
Classifier: Operating System :: OS Independent
Requires-Python: >=3.11
License-File: LICENSE
Requires-Dist: werkflow-core
Requires-Dist: werkflow-file
Requires-Dist: werkflow-secrets
Requires-Dist: werkflow-shell
Requires-Dist: werkflow-system
Requires-Dist: werkflow-http
Requires-Dist: pydantic
Dynamic: license-file
